hippotrainer/__init__.py
hippotrainer/dr_mad.py
hippotrainer/hoag.py
hippotrainer/hyper_optimizer.py
hippotrainer/neumann.py
hippotrainer/t1_t2.py
hippotrainer-1.0.0.dist-info/licenses/LICENSE
hippotrainer-1.0.0.dist-info/METADATA
hippotrainer-1.0.0.dist-info/WHEEL
hippotrainer-1.0.0.dist-info/top_level.txt
hippotrainer-1.0.0.dist-info/RECORD
